repute/__init__.py
repute/analysis.py
repute/cache.py
repute/constants.py
repute/data.py
repute/main.py
repute/requirements.py
repute/github/analytics.py
repute/github/data.py
repute/github/web.py
repute/pypi/analytics.py
repute/pypi/github.py
repute/pypi/stats.py
repute/pypi/web.py
repute-0.1.5.dist-info/METADATA
repute-0.1.5.dist-info/WHEEL
repute-0.1.5.dist-info/entry_points.txt
repute-0.1.5.dist-info/licenses/LICENSE
repute-0.1.5.dist-info/RECORD
