Metadata-Version: 2.4
Name: repute
Version: 0.1.5
Summary: Python package dependency analytics. Know what you depend on!
Project-URL: Source, https://github.com/zkurtz/repute
Author-email: Zach Kurtz <zkurtz@gmail.com>
License-File: LICENSE
Requires-Python: >=3.10
Requires-Dist: attrs>=25.3
Requires-Dist: click>=8
Requires-Dist: dummio>=1.10
Requires-Dist: orjson>=3.10.15
Requires-Dist: pandahandler>=0.7.4
Requires-Dist: pandas>=1.5
Requires-Dist: pypistats>=1.8
Requires-Dist: requests>=2.32.3
Requires-Dist: tqdm>=4.67.1
